CHANGELOG
COPYING
MANIFEST.in
README
arithmetic
arithmetic.py
calc.py
editor-gtk.py
editor-tk.py
editor-wx.py
editor.ui
manual.html
manual.rst
pyroom-0.4.1-arithmetic.patch
setup.py
tutorial-1
tutorial-2
arithmetic.egg-info/PKG-INFO
arithmetic.egg-info/SOURCES.txt
arithmetic.egg-info/dependency_links.txt
arithmetic.egg-info/top_level.txt
vim-plugin/arithmetic.txt
vim-plugin/arithmetic.vim
vim-plugin/install.sh
vim-plugin/tutorial.txt
vim-plugin/wrapper.py