Metadata-Version: 1.1
Name: arithmetic
Version: 0.6.2
Summary: Arithmetic module
Home-page: http://pp.com.mx/python/arithmetic/
Author: Patricio Paez
Author-email: pp@pp.com.mx
License: GNU GPL v2 or later
Platform: any
Classifier: Development Status :: 3 - Alpha
Classifier: Topic :: Text Processing
Classifier: Programming Language :: Python :: 2
Classifier: Programming Language :: Python :: 3
